Metadata-Version: 2.1
Name: code-dir
Version: 0.0.1
Summary: cool package
Author: Abdulsalam Raja
License-File: LICENSE.txt
